autocloudreporter.py
autocloudreporter-1.0.4.dist-info/licenses/COPYING
autocloudreporter-1.0.4.dist-info/METADATA
autocloudreporter-1.0.4.dist-info/WHEEL
autocloudreporter-1.0.4.dist-info/top_level.txt
autocloudreporter-1.0.4.dist-info/RECORD
